p9fs/__init__.py
py9p/__init__.py
py9p/__main__.py
py9p/fid.py
py9p/fuse9p.py
py9p/pki.py
py9p/py9p.py
py9p/utils.py
p9fs-0.0.4.dist-info/LICENSE
p9fs-0.0.4.dist-info/METADATA
p9fs-0.0.4.dist-info/WHEEL
p9fs-0.0.4.dist-info/entry_points.txt
p9fs-0.0.4.dist-info/top_level.txt
p9fs-0.0.4.dist-info/RECORD
