Metadata-Version: 2.1
Name: p9fs
Version: 0.0.4
Summary: 9P implementation of Python fsspec
Author-email: Pavel Chekin <pbchekin@gmail.com>
License: Apache License
Project-URL: Homepage, https://github.com/pbchekin/p9fs-py
Project-URL: Source, https://github.com/pbchekin/p9fs-py
Classifier: Development Status :: 3 - Alpha
Classifier: License :: OSI Approved :: Apache Software License
Classifier: Programming Language :: Python :: 3
Classifier: Operating System :: OS Independent
Requires-Python: >=3.8
License-File: LICENSE
Requires-Dist: fsspec
Provides-Extra: tests
Requires-Dist: pytest ; extra == 'tests'
